CHANGES.txt
LICENSE.txt
README.txt
bootstrap.py
buildout.cfg
setup.py
src/getpaid/__init__.py
src/getpaid.googlecheckout.egg-info/PKG-INFO
src/getpaid.googlecheckout.egg-info/SOURCES.txt
src/getpaid.googlecheckout.egg-info/dependency_links.txt
src/getpaid.googlecheckout.egg-info/namespace_packages.txt
src/getpaid.googlecheckout.egg-info/not-zip-safe
src/getpaid.googlecheckout.egg-info/requires.txt
src/getpaid.googlecheckout.egg-info/top_level.txt
src/getpaid/googlecheckout/README.txt
src/getpaid/googlecheckout/__init__.py
src/getpaid/googlecheckout/configure.zcml
src/getpaid/googlecheckout/controller.py
src/getpaid/googlecheckout/googlecheckout-browser.txt
src/getpaid/googlecheckout/googlecheckout.py
src/getpaid/googlecheckout/googlecheckout.txt
src/getpaid/googlecheckout/i18n.sh
src/getpaid/googlecheckout/interfaces.py
src/getpaid/googlecheckout/overrides.zcml
src/getpaid/googlecheckout/shipping.py
src/getpaid/googlecheckout/vocabulary.py
src/getpaid/googlecheckout/vocabulary.zcml
src/getpaid/googlecheckout/browser/__init__.py
src/getpaid/googlecheckout/browser/button.py
src/getpaid/googlecheckout/browser/cart.py
src/getpaid/googlecheckout/browser/checkout.py
src/getpaid/googlecheckout/browser/configure.zcml
src/getpaid/googlecheckout/browser/notification.py
src/getpaid/googlecheckout/browser/overrides.zcml
src/getpaid/googlecheckout/browser/portlets/__init__.py
src/getpaid/googlecheckout/browser/portlets/cart.py
src/getpaid/googlecheckout/browser/portlets/overrides.zcml
src/getpaid/googlecheckout/browser/templates/cart-actions.pt
src/getpaid/googlecheckout/browser/templates/portlet-cart.pt
src/getpaid/googlecheckout/locales/empty.pt
src/getpaid/googlecheckout/locales/getpaid.googlecheckout.pot
src/getpaid/googlecheckout/locales/manual.pot
src/getpaid/googlecheckout/locales/en/LC_MESSAGES/getpaid.googlecheckout.mo
src/getpaid/googlecheckout/locales/en/LC_MESSAGES/getpaid.googlecheckout.po
src/getpaid/googlecheckout/locales/es/LC_MESSAGES/getpaid.googlecheckout.mo
src/getpaid/googlecheckout/locales/es/LC_MESSAGES/getpaid.googlecheckout.po
src/getpaid/googlecheckout/locales/it/LC_MESSAGES/getpaid.googlecheckout.mo
src/getpaid/googlecheckout/locales/it/LC_MESSAGES/getpaid.googlecheckout.po
src/getpaid/googlecheckout/tests/__init__.py
src/getpaid/googlecheckout/tests/browser.py
